README.md
setup.cfg
setup.py
dpyacl/__init__.py
dpyacl.egg-info/PKG-INFO
dpyacl.egg-info/SOURCES.txt
dpyacl.egg-info/dependency_links.txt
dpyacl.egg-info/requires.txt
dpyacl.egg-info/top_level.txt
dpyacl/core/__init__.py
dpyacl/core/collections.py
dpyacl/core/state.py
dpyacl/core/stop_criteria.py
dpyacl/core/misc/__init__.py
dpyacl/core/misc/misc.py
dpyacl/experiment/__init__.py
dpyacl/experiment/context.py
dpyacl/experiment/experiment_analyser.py
dpyacl/learner/__init__.py
dpyacl/learner/active_learning.py
dpyacl/metrics/__init__.py
dpyacl/metrics/evaluation.py
dpyacl/oracle/__init__.py
dpyacl/oracle/oracle.py
dpyacl/scenario/__init__.py
dpyacl/scenario/scenario.py
dpyacl/strategies/__init__.py
dpyacl/strategies/stategies.py
dpyacl/strategies/single_label/__init__.py
dpyacl/strategies/single_label/error_reduction.py
dpyacl/strategies/single_label/query_by_comitee.py
dpyacl/strategies/single_label/random_sampling.py
dpyacl/strategies/single_label/uncertainty_sampling.py
test/test_context.py
test/test_example_AL.py
test/test_example_hmeq.py
test/test_example_keras.py
test/test_example_regression.py
test/test_metrics.py
test/test_single_label_pool_based_query_strategies.py
test/test_stop_criteria.py