Metadata-Version: 2.1
Name: dpyacl
Version: 0.3.3
Summary: Distributed Python Active Learning library
Home-page: https://github.com/a24lorie/DPyACL
Author: Alfredo Lorie
Author-email: a24lorie@gmail.com
License: GNU
Platform: UNKNOWN
